cx_Freeze/__init__.py
cx_Freeze/common.py
cx_Freeze/dist.py
cx_Freeze/finder.py
cx_Freeze/freezer.py
cx_Freeze/hooks.py
cx_Freeze/macdist.py
cx_Freeze/main.py
cx_Freeze/setupwriter.py
cx_Freeze/util.cp35-win_amd64.pyd
cx_Freeze/windist.py
cx_Freeze/__pycache__/__init__.cpython-35.opt-1.pyc
cx_Freeze/__pycache__/common.cpython-35.opt-1.pyc
cx_Freeze/__pycache__/dist.cpython-35.opt-1.pyc
cx_Freeze/__pycache__/finder.cpython-35.opt-1.pyc
cx_Freeze/__pycache__/freezer.cpython-35.opt-1.pyc
cx_Freeze/__pycache__/hooks.cpython-35.opt-1.pyc
cx_Freeze/__pycache__/macdist.cpython-35.opt-1.pyc
cx_Freeze/__pycache__/main.cpython-35.opt-1.pyc
cx_Freeze/__pycache__/setupwriter.cpython-35.opt-1.pyc
cx_Freeze/__pycache__/windist.cpython-35.opt-1.pyc
cx_Freeze/bases/Console.exe
cx_Freeze/bases/ConsoleKeepPath.exe
cx_Freeze/bases/Win32GUI.exe
cx_Freeze/initscripts/Console.py
cx_Freeze/initscripts/ConsoleKeepPath.py
cx_Freeze/initscripts/ConsoleSetLibPath.py
cx_Freeze/initscripts/SharedLib.py
cx_Freeze/initscripts/SharedLibSource.py
cx_Freeze/initscripts/__pycache__/Console.cpython-35.opt-1.pyc
cx_Freeze/initscripts/__pycache__/ConsoleKeepPath.cpython-35.opt-1.pyc
cx_Freeze/initscripts/__pycache__/ConsoleSetLibPath.cpython-35.opt-1.pyc
cx_Freeze/initscripts/__pycache__/SharedLib.cpython-35.opt-1.pyc
cx_Freeze/initscripts/__pycache__/SharedLibSource.cpython-35.opt-1.pyc
cx_Freeze/samples/PyQt4/PyQt4app.py
cx_Freeze/samples/PyQt4/setup.py
cx_Freeze/samples/PyQt4/__pycache__/PyQt4app.cpython-35.opt-1.pyc
cx_Freeze/samples/PyQt4/__pycache__/setup.cpython-35.opt-1.pyc
cx_Freeze/samples/Tkinter/SimpleTkApp.py
cx_Freeze/samples/Tkinter/setup.py
cx_Freeze/samples/Tkinter/__pycache__/SimpleTkApp.cpython-35.opt-1.pyc
cx_Freeze/samples/Tkinter/__pycache__/setup.cpython-35.opt-1.pyc
cx_Freeze/samples/advanced/advanced_1.py
cx_Freeze/samples/advanced/advanced_2.py
cx_Freeze/samples/advanced/setup.py
gns3_cx_Freeze-4.3.6.dist-info/DESCRIPTION.rst
gns3_cx_Freeze-4.3.6.dist-info/METADATA
gns3_cx_Freeze-4.3.6.dist-info/RECORD
gns3_cx_Freeze-4.3.6.dist-info/WHEEL
gns3_cx_Freeze-4.3.6.dist-info/metadata.json
gns3_cx_Freeze-4.3.6.dist-info/top_level.txt
