Metadata-Version: 2.0
Name: gns3-cx-Freeze
Version: 4.3.6
Summary: Temporary fork of cx_Freeze 4.x with Python 3.5 support.
Home-page: http://cx-freeze.sourceforge.net
Author: Julien Duponchelle
Author-email: julien@gns3.net
License: Python Software Foundation License
Keywords: freeze
Platform: UNKNOWN
Classifier: Development Status :: 5 - Production/Stable
Classifier: Intended Audience :: Developers
Classifier: License :: OSI Approved :: Python Software Foundation License
Classifier: Natural Language :: English
Classifier: Operating System :: OS Independent
Classifier: Programming Language :: C
Classifier: Programming Language :: Python
Classifier: Programming Language :: Python :: 2
Classifier: Programming Language :: Python :: 3
Classifier: Topic :: Software Development :: Build Tools
Classifier: Topic :: Software Development :: Libraries :: Python Modules
Classifier: Topic :: System :: Software Distribution
Classifier: Topic :: Utilities
